cs_sync/__init__.py
cs_sync/__main__.py
cs_sync/github.py
cs_sync/handlers.py
cs_sync/helpers.py
cs_sync/main.py
cs_sync-0.1.6.dist-info/LICENSE
cs_sync-0.1.6.dist-info/METADATA
cs_sync-0.1.6.dist-info/WHEEL
cs_sync-0.1.6.dist-info/entry_points.txt
cs_sync-0.1.6.dist-info/top_level.txt
cs_sync-0.1.6.dist-info/RECORD
