Metadata-Version: 2.1
Name: cs-sync
Version: 0.1.6
Home-page: https://github.com/AceofSpades5757/cs-sync
Author: Kyle L. Davis
Author-email: AceofSpades5757.github@gmail.com
License: MIT
Classifier: Programming Language :: Python :: 3
Classifier: Operating System :: OS Independent
Classifier: License :: OSI Approved :: MIT License
Classifier: Programming Language :: Python :: 3.6
Classifier: Programming Language :: Python :: 3.7
Classifier: Programming Language :: Python :: 3.8
Classifier: Programming Language :: Python :: 3.9
Classifier: Programming Language :: Python :: 3.10
Requires-Python: >=3.6
License-File: LICENSE
Requires-Dist: typer
Requires-Dist: PyYAML
Requires-Dist: blessed
